README.md
setup.py
circonusapi/__init__.py
circonusapi/circonusapi.py
circonusapi/circonusdata.py
circonusapi/circonussubmit.py
circonusapi/config.py
circonusapi.egg-info/PKG-INFO
circonusapi.egg-info/SOURCES.txt
circonusapi.egg-info/dependency_links.txt
circonusapi.egg-info/requires.txt
circonusapi.egg-info/top_level.txt
test/test_circonusapi.py
test/test_circonusdata.py